README.txt
setup.py
docs/HISTORY.txt
docs/INSTALL.txt
docs/LICENSE.GPL
docs/LICENSE.txt
medialog/__init__.py
medialog.portlet.donate.egg-info/PKG-INFO
medialog.portlet.donate.egg-info/SOURCES.txt
medialog.portlet.donate.egg-info/dependency_links.txt
medialog.portlet.donate.egg-info/entry_points.txt
medialog.portlet.donate.egg-info/namespace_packages.txt
medialog.portlet.donate.egg-info/not-zip-safe
medialog.portlet.donate.egg-info/requires.txt
medialog.portlet.donate.egg-info/top_level.txt
medialog/portlet/__init__.py
medialog/portlet/donate/__init__.py
medialog/portlet/donate/configure.zcml
medialog/portlet/donate/donateportlet.pt
medialog/portlet/donate/donateportlet.py
medialog/portlet/donate/version.txt
medialog/portlet/donate/profiles/default/metadata.xml
medialog/portlet/donate/profiles/default/portlets.xml
medialog/portlet/donate/tests/__init__.py
medialog/portlet/donate/tests/base.py
medialog/portlet/donate/tests/test_portlet.py