Metadata-Version: 1.0
Name: medialog.portlet.donate
Version: 0.3
Summary: A simple donate button
Home-page: http://medialog.no
Author: Espen Moe-Nilssen
Author-email: espen@medialog.no
License: GPL
Platform: UNKNOWN
Classifier: Framework :: Plone
Classifier: Programming Language :: Python
Classifier: Topic :: Software Development :: Libraries :: Python Modules
